no_slop/__init__.py
no_slop/_version.py
no_slop/flake8_plugin.py
no_slop/mypy_plugin.py
no_slop/unused_defaults.py
no_slop/rules/__init__.py
no_slop/rules/flake8/__init__.py
no_slop/rules/flake8/ai_artifacts.py
no_slop/rules/flake8/ascii_art.py
no_slop/rules/flake8/base.py
no_slop/rules/flake8/docstrings.py
no_slop/rules/flake8/emojis.py
no_slop/rules/flake8/idiomatic.py
no_slop/rules/flake8/indirect_access.py
no_slop/rules/flake8/local_imports.py
no_slop/rules/flake8/redundant_patterns.py
no_slop/rules/flake8/ai_patterns/__init__.py
no_slop/rules/flake8/ai_patterns/annotations.py
no_slop/rules/flake8/ai_patterns/ast_utils.py
no_slop/rules/flake8/ai_patterns/check.py
no_slop/rules/flake8/ai_patterns/comments.py
no_slop/rules/flake8/ai_patterns/constants.py
no_slop/rules/flake8/ai_patterns/indices.py
no_slop/rules/flake8/ai_patterns/visitor.py
no_slop/rules/mypy/__init__.py
no_slop/rules/mypy/base.py
no_slop/rules/mypy/callable.py
no_slop/rules/mypy/delattr.py
no_slop/rules/mypy/dict_get.py
no_slop/rules/mypy/getattr.py
no_slop/rules/mypy/hasattr.py
no_slop/rules/mypy/isinstance.py
no_slop/rules/mypy/issubclass.py
no_slop/rules/mypy/setattr.py
no_slop-0.5.0.dist-info/METADATA
no_slop-0.5.0.dist-info/WHEEL
no_slop-0.5.0.dist-info/entry_points.txt
no_slop-0.5.0.dist-info/licenses/LICENSE
no_slop-0.5.0.dist-info/RECORD
