Metadata-Version: 2.4
Name: no-slop
Version: 0.5.0
Summary: Detect AI-generated code patterns via static analysis
Project-URL: Homepage, https://github.com/HardMax71/no-slop
Project-URL: Repository, https://github.com/HardMax71/no-slop
Project-URL: Issues, https://github.com/HardMax71/no-slop/issues
Author: HardMax71
License: MIT
License-File: LICENSE
Keywords: ai,code-quality,flake8,linter,mypy,static-analysis
Classifier: Development Status :: 3 - Alpha
Classifier: Framework :: Flake8
Classifier: Intended Audience :: Developers
Classifier: License :: OSI Approved :: MIT License
Classifier: Programming Language :: Python :: 3
Classifier: Programming Language :: Python :: 3.10
Classifier: Programming Language :: Python :: 3.11
Classifier: Programming Language :: Python :: 3.12
Classifier: Programming Language :: Python :: 3.13
Classifier: Topic :: Software Development :: Quality Assurance
Requires-Python: >=3.10
Requires-Dist: mypy>=1.0
Requires-Dist: packaging>=23.0
Requires-Dist: tomli>=2.0
Provides-Extra: dev
Requires-Dist: flake8>=6.0; extra == 'dev'
Requires-Dist: pytest-cov>=4.0; extra == 'dev'
Requires-Dist: pytest>=7.0; extra == 'dev'
Requires-Dist: ruff>=0.1; extra == 'dev'
